[{"RawFeatureName": "Customer_Age", "TypeDetected": "Categorical", "Dropped": "No", "EngineeredFeatureCount": 45, "Transformations": ["StringCast-CharGramCountVectorizer"], "TransformationParams": {"Transformer1": {"Input": ["Customer_Age"], "TransformationFunction": "StringCast", "Operator": null, "FeatureType": "Categorical", "ShouldOutput": false, "TransformationParams": {}}, "Transformer2": {"Input": ["Transformer1"], "TransformationFunction": "CountVectorizer", "Operator": "CharGram", "FeatureType": null, "ShouldOutput": true, "TransformationParams": {"analyzer": "word", "binary": true, "decode_error": "strict", "encoding": "utf-8", "input": "content", "lowercase": true, "max_df": 1.0, "max_features": null, "min_df": 1, "ngram_range": [1, 1], "stop_words": null, "strip_accents": null, "token_pattern": "(?u)\\b\\w\\w+\\b", "vocabulary": null}}}}, {"RawFeatureName": "Gender", "TypeDetected": "Categorical", "Dropped": "No", "EngineeredFeatureCount": 1, "Transformations": ["ModeCatImputer-StringCast-LabelEncoder"], "TransformationParams": {"Transformer1": {"Input": ["Gender"], "TransformationFunction": "CatImputer", "Operator": "Mode", "FeatureType": "Categorical", "ShouldOutput": true, "TransformationParams": {"copy": true}}, "Transformer2": {"Input": ["Transformer1"], "TransformationFunction": "StringCast", "Operator": null, "FeatureType": null, "ShouldOutput": false, "TransformationParams": {}}, "Transformer3": {"Input": ["Transformer2"], "TransformationFunction": "LabelEncoder", "Operator": null, "FeatureType": null, "ShouldOutput": true, "TransformationParams": {"hashing_seed_val": 314489979}}}}, {"RawFeatureName": "Dependent_count", "TypeDetected": "Categorical", "Dropped": "No", "EngineeredFeatureCount": 6, "Transformations": ["StringCast-CharGramCountVectorizer"], "TransformationParams": {"Transformer1": {"Input": ["Dependent_count"], "TransformationFunction": "StringCast", "Operator": null, "FeatureType": "Categorical", "ShouldOutput": false, "TransformationParams": {}}, "Transformer2": {"Input": ["Transformer1"], "TransformationFunction": "CountVectorizer", "Operator": "CharGram", "FeatureType": null, "ShouldOutput": true, "TransformationParams": {"analyzer": "word", "binary": true, "decode_error": "strict", "encoding": "utf-8", "input": "content", "lowercase": true, "max_df": 1.0, "max_features": null, "min_df": 1, "ngram_range": [1, 1], "stop_words": null, "strip_accents": null, "token_pattern": "(?u)\\b\\w\\w+\\b", "vocabulary": null}}}}, {"RawFeatureName": "Education_Level", "TypeDetected": "Categorical", "Dropped": "No", "EngineeredFeatureCount": 7, "Transformations": ["StringCast-CharGramCountVectorizer"], "TransformationParams": {"Transformer1": {"Input": ["Education_Level"], "TransformationFunction": "StringCast", "Operator": null, "FeatureType": "Categorical", "ShouldOutput": false, "TransformationParams": {}}, "Transformer2": {"Input": ["Transformer1"], "TransformationFunction": "CountVectorizer", "Operator": "CharGram", "FeatureType": null, "ShouldOutput": true, "TransformationParams": {"analyzer": "word", "binary": true, "decode_error": "strict", "encoding": "utf-8", "input": "content", "lowercase": true, "max_df": 1.0, "max_features": null, "min_df": 1, "ngram_range": [1, 1], "stop_words": null, "strip_accents": null, "token_pattern": "(?u)\\b\\w\\w+\\b", "vocabulary": null}}}}, {"RawFeatureName": "Marital_Status", "TypeDetected": "Categorical", "Dropped": "No", "EngineeredFeatureCount": 4, "Transformations": ["StringCast-CharGramCountVectorizer"], "TransformationParams": {"Transformer1": {"Input": ["Marital_Status"], "TransformationFunction": "StringCast", "Operator": null, "FeatureType": "Categorical", "ShouldOutput": false, "TransformationParams": {}}, "Transformer2": {"Input": ["Transformer1"], "TransformationFunction": "CountVectorizer", "Operator": "CharGram", "FeatureType": null, "ShouldOutput": true, "TransformationParams": {"analyzer": "word", "binary": true, "decode_error": "strict", "encoding": "utf-8", "input": "content", "lowercase": true, "max_df": 1.0, "max_features": null, "min_df": 1, "ngram_range": [1, 1], "stop_words": null, "strip_accents": null, "token_pattern": "(?u)\\b\\w\\w+\\b", "vocabulary": null}}}}, {"RawFeatureName": "Income_Category", "TypeDetected": "Categorical", "Dropped": "No", "EngineeredFeatureCount": 6, "Transformations": ["StringCast-CharGramCountVectorizer"], "TransformationParams": {"Transformer1": {"Input": ["Income_Category"], "TransformationFunction": "StringCast", "Operator": null, "FeatureType": "Categorical", "ShouldOutput": false, "TransformationParams": {}}, "Transformer2": {"Input": ["Transformer1"], "TransformationFunction": "CountVectorizer", "Operator": "CharGram", "FeatureType": null, "ShouldOutput": true, "TransformationParams": {"analyzer": "word", "binary": true, "decode_error": "strict", "encoding": "utf-8", "input": "content", "lowercase": true, "max_df": 1.0, "max_features": null, "min_df": 1, "ngram_range": [1, 1], "stop_words": null, "strip_accents": null, "token_pattern": "(?u)\\b\\w\\w+\\b", "vocabulary": null}}}}, {"RawFeatureName": "Card_Category", "TypeDetected": "Categorical", "Dropped": "No", "EngineeredFeatureCount": 4, "Transformations": ["StringCast-CharGramCountVectorizer"], "TransformationParams": {"Transformer1": {"Input": ["Card_Category"], "TransformationFunction": "StringCast", "Operator": null, "FeatureType": "Categorical", "ShouldOutput": false, "TransformationParams": {}}, "Transformer2": {"Input": ["Transformer1"], "TransformationFunction": "CountVectorizer", "Operator": "CharGram", "FeatureType": null, "ShouldOutput": true, "TransformationParams": {"analyzer": "word", "binary": true, "decode_error": "strict", "encoding": "utf-8", "input": "content", "lowercase": true, "max_df": 1.0, "max_features": null, "min_df": 1, "ngram_range": [1, 1], "stop_words": null, "strip_accents": null, "token_pattern": "(?u)\\b\\w\\w+\\b", "vocabulary": null}}}}, {"RawFeatureName": "Months_on_book", "TypeDetected": "Categorical", "Dropped": "No", "EngineeredFeatureCount": 44, "Transformations": ["StringCast-CharGramCountVectorizer"], "TransformationParams": {"Transformer1": {"Input": ["Months_on_book"], "TransformationFunction": "StringCast", "Operator": null, "FeatureType": "Categorical", "ShouldOutput": false, "TransformationParams": {}}, "Transformer2": {"Input": ["Transformer1"], "TransformationFunction": "CountVectorizer", "Operator": "CharGram", "FeatureType": null, "ShouldOutput": true, "TransformationParams": {"analyzer": "word", "binary": true, "decode_error": "strict", "encoding": "utf-8", "input": "content", "lowercase": true, "max_df": 1.0, "max_features": null, "min_df": 1, "ngram_range": [1, 1], "stop_words": null, "strip_accents": null, "token_pattern": "(?u)\\b\\w\\w+\\b", "vocabulary": null}}}}, {"RawFeatureName": "Total_Relationship_Count", "TypeDetected": "Categorical", "Dropped": "No", "EngineeredFeatureCount": 6, "Transformations": ["StringCast-CharGramCountVectorizer"], "TransformationParams": {"Transformer1": {"Input": ["Total_Relationship_Count"], "TransformationFunction": "StringCast", "Operator": null, "FeatureType": "Categorical", "ShouldOutput": false, "TransformationParams": {}}, "Transformer2": {"Input": ["Transformer1"], "TransformationFunction": "CountVectorizer", "Operator": "CharGram", "FeatureType": null, "ShouldOutput": true, "TransformationParams": {"analyzer": "word", "binary": true, "decode_error": "strict", "encoding": "utf-8", "input": "content", "lowercase": true, "max_df": 1.0, "max_features": null, "min_df": 1, "ngram_range": [1, 1], "stop_words": null, "strip_accents": null, "token_pattern": "(?u)\\b\\w\\w+\\b", "vocabulary": null}}}}, {"RawFeatureName": "Months_Inactive_12_mon", "TypeDetected": "Categorical", "Dropped": "No", "EngineeredFeatureCount": 7, "Transformations": ["StringCast-CharGramCountVectorizer"], "TransformationParams": {"Transformer1": {"Input": ["Months_Inactive_12_mon"], "TransformationFunction": "StringCast", "Operator": null, "FeatureType": "Categorical", "ShouldOutput": false, "TransformationParams": {}}, "Transformer2": {"Input": ["Transformer1"], "TransformationFunction": "CountVectorizer", "Operator": "CharGram", "FeatureType": null, "ShouldOutput": true, "TransformationParams": {"analyzer": "word", "binary": true, "decode_error": "strict", "encoding": "utf-8", "input": "content", "lowercase": true, "max_df": 1.0, "max_features": null, "min_df": 1, "ngram_range": [1, 1], "stop_words": null, "strip_accents": null, "token_pattern": "(?u)\\b\\w\\w+\\b", "vocabulary": null}}}}, {"RawFeatureName": "Contacts_Count_12_mon", "TypeDetected": "Categorical", "Dropped": "No", "EngineeredFeatureCount": 7, "Transformations": ["StringCast-CharGramCountVectorizer"], "TransformationParams": {"Transformer1": {"Input": ["Contacts_Count_12_mon"], "TransformationFunction": "StringCast", "Operator": null, "FeatureType": "Categorical", "ShouldOutput": false, "TransformationParams": {}}, "Transformer2": {"Input": ["Transformer1"], "TransformationFunction": "CountVectorizer", "Operator": "CharGram", "FeatureType": null, "ShouldOutput": true, "TransformationParams": {"analyzer": "word", "binary": true, "decode_error": "strict", "encoding": "utf-8", "input": "content", "lowercase": true, "max_df": 1.0, "max_features": null, "min_df": 1, "ngram_range": [1, 1], "stop_words": null, "strip_accents": null, "token_pattern": "(?u)\\b\\w\\w+\\b", "vocabulary": null}}}}, {"RawFeatureName": "Credit_Limit", "TypeDetected": "Numeric", "Dropped": "No", "EngineeredFeatureCount": 9, "Transformations": ["MeanImputer"], "TransformationParams": {"Transformer1": {"Input": ["Credit_Limit"], "TransformationFunction": "Imputer", "Operator": "Mean", "FeatureType": "Numeric", "ShouldOutput": true, "TransformationParams": {"add_indicator": false, "copy": true, "fill_value": null, "missing_values": NaN, "strategy": "mean", "verbose": 0}}}}, {"RawFeatureName": "Total_Revolving_Bal", "TypeDetected": "Numeric", "Dropped": "No", "EngineeredFeatureCount": 9, "Transformations": ["MeanImputer"], "TransformationParams": {"Transformer1": {"Input": ["Total_Revolving_Bal"], "TransformationFunction": "Imputer", "Operator": "Mean", "FeatureType": "Numeric", "ShouldOutput": true, "TransformationParams": {"add_indicator": false, "copy": true, "fill_value": null, "missing_values": NaN, "strategy": "mean", "verbose": 0}}}}, {"RawFeatureName": "Avg_Open_To_Buy", "TypeDetected": "Numeric", "Dropped": "No", "EngineeredFeatureCount": 9, "Transformations": ["MeanImputer"], "TransformationParams": {"Transformer1": {"Input": ["Avg_Open_To_Buy"], "TransformationFunction": "Imputer", "Operator": "Mean", "FeatureType": "Numeric", "ShouldOutput": true, "TransformationParams": {"add_indicator": false, "copy": true, "fill_value": null, "missing_values": NaN, "strategy": "mean", "verbose": 0}}}}, {"RawFeatureName": "Total_Amt_Chng_Q4_Q1", "TypeDetected": "Numeric", "Dropped": "No", "EngineeredFeatureCount": 9, "Transformations": ["MeanImputer"], "TransformationParams": {"Transformer1": {"Input": ["Total_Amt_Chng_Q4_Q1"], "TransformationFunction": "Imputer", "Operator": "Mean", "FeatureType": "Numeric", "ShouldOutput": true, "TransformationParams": {"add_indicator": false, "copy": true, "fill_value": null, "missing_values": NaN, "strategy": "mean", "verbose": 0}}}}, {"RawFeatureName": "Total_Trans_Amt", "TypeDetected": "Numeric", "Dropped": "No", "EngineeredFeatureCount": 9, "Transformations": ["MeanImputer"], "TransformationParams": {"Transformer1": {"Input": ["Total_Trans_Amt"], "TransformationFunction": "Imputer", "Operator": "Mean", "FeatureType": "Numeric", "ShouldOutput": true, "TransformationParams": {"add_indicator": false, "copy": true, "fill_value": null, "missing_values": NaN, "strategy": "mean", "verbose": 0}}}}, {"RawFeatureName": "Total_Trans_Ct", "TypeDetected": "Numeric", "Dropped": "No", "EngineeredFeatureCount": 9, "Transformations": ["MeanImputer"], "TransformationParams": {"Transformer1": {"Input": ["Total_Trans_Ct"], "TransformationFunction": "Imputer", "Operator": "Mean", "FeatureType": "Numeric", "ShouldOutput": true, "TransformationParams": {"add_indicator": false, "copy": true, "fill_value": null, "missing_values": NaN, "strategy": "mean", "verbose": 0}}}}, {"RawFeatureName": "Total_Ct_Chng_Q4_Q1", "TypeDetected": "Numeric", "Dropped": "No", "EngineeredFeatureCount": 9, "Transformations": ["MeanImputer"], "TransformationParams": {"Transformer1": {"Input": ["Total_Ct_Chng_Q4_Q1"], "TransformationFunction": "Imputer", "Operator": "Mean", "FeatureType": "Numeric", "ShouldOutput": true, "TransformationParams": {"add_indicator": false, "copy": true, "fill_value": null, "missing_values": NaN, "strategy": "mean", "verbose": 0}}}}, {"RawFeatureName": "Avg_Utilization_Ratio", "TypeDetected": "Numeric", "Dropped": "No", "EngineeredFeatureCount": 9, "Transformations": ["MeanImputer"], "TransformationParams": {"Transformer1": {"Input": ["Avg_Utilization_Ratio"], "TransformationFunction": "Imputer", "Operator": "Mean", "FeatureType": "Numeric", "ShouldOutput": true, "TransformationParams": {"add_indicator": false, "copy": true, "fill_value": null, "missing_values": NaN, "strategy": "mean", "verbose": 0}}}}, {"RawFeatureName": "Credit_Limit-Total_Revolving_Bal-Avg_Open_To_Buy-Total_Amt_Chng_Q4_Q1-Total_Trans_Amt-Total_Trans_Ct-Total_Ct_Chng_Q4_Q1-Avg_Utilization_Ratio", "TypeDetected": "Numeric", "Dropped": "No", "EngineeredFeatureCount": 0, "Transformations": ["MeanImputer-MaxAbsScaler-MiniBatchKMeans"], "TransformationParams": {"Transformer1": {"Input": ["Credit_Limit", "Total_Revolving_Bal", "Avg_Open_To_Buy", "Total_Amt_Chng_Q4_Q1", "Total_Trans_Amt", "Total_Trans_Ct", "Total_Ct_Chng_Q4_Q1", "Avg_Utilization_Ratio"], "TransformationFunction": "Imputer", "Operator": "Mean", "FeatureType": "Numeric", "ShouldOutput": true, "TransformationParams": {"add_indicator": false, "copy": true, "fill_value": null, "missing_values": NaN, "strategy": "mean", "verbose": 0}}, "Transformer2": {"Input": ["Transformer1"], "TransformationFunction": "MaxAbsScaler", "Operator": null, "FeatureType": null, "ShouldOutput": true, "TransformationParams": {"copy": true}}, "Transformer3": {"Input": ["Transformer2"], "TransformationFunction": "MiniBatchKMeans", "Operator": null, "FeatureType": null, "ShouldOutput": true, "TransformationParams": {"batch_size": 100, "compute_labels": true, "init_size": null, "max_iter": 100, "max_no_improvement": 10, "n_clusters": 8, "n_init": 3, "random_state": null, "reassignment_ratio": 0.01, "tol": 0.0, "verbose": 0}}}}]